Lab2/210050037/Q2/full_adder.vhd
library IEEE;
use IEEE.std_logic_1164.all;

entity fulladder is
    port(a, b ,c : in std_logic;
    sum: out std_logic;
    cout: out std_logic);
end entity;

architecture behaviour of fulladder is
    begin
       sum <= a xor b xor c;
       cout <= (a and b) or (b and c) or (c and a);
    end architecture;

Lab2/210050037/Q2/RCA8.vhd
    
library IEEE;
use IEEE.std_logic_1164.all;

entity RCA8 is
    port(a, b: in std_logic_vector(7 downto 0);
    sum: out std_logic_vector(7 downto 0);
    cout: out std_logic);
end entity;
    
architecture behaviour of RCA8 is
    component fulladder is
        port(a, b ,c : in std_logic;
        sum: out std_logic;
        cout: out std_logic);
    end component;
    signal cin,temp,temp1,temp2,temp3,temp4,temp5,temp6,temp7:std_logic;
begin
   cin<='0';
    dut_instance: fulladder port map(
    a=>a(0),b=>b(0),c=>cin,sum=>sum(0),cout=>temp
    );
    dut_instance1: fulladder port map(
    a=>a(1),b=>b(1),c=>temp,sum=>sum(1),cout=>temp1
    );
    dut_instance2: fulladder port map(
    a=>a(2),b=>b(2),c=>temp1,sum=>sum(2),cout=>temp2
    );
    dut_instance3: fulladder port map(
    a=>a(3),b=>b(3),c=>temp2,sum=>sum(3),cout=>temp3
    );
    dut_instance4: fulladder port map(
    a=>a(4),b=>b(4),c=>temp3,sum=>sum(4),cout=>temp4
    );
    dut_instance5: fulladder port map(
    a=>a(5),b=>b(5),c=>temp4,sum=>sum(5),cout=>temp5
    );
    dut_instance6: fulladder port map(
    a=>a(6),b=>b(6),c=>temp5,sum=>sum(6),cout=>temp6
    );
    dut_instance7: fulladder port map(
    a=>a(7),b=>b(7),c=>temp6,sum=>sum(7),cout=>temp7
    );
    cout<=temp7;
end architecture;

Lab2/210050037/Q2/RCA8_tb.vhd
library IEEE;
use IEEE.std_logic_1164.all;

entity Testbench_RCA8 is
end entity;

architecture tb of Testbench_RCA8 is


    component RCA8 is
        port(a, b: in std_logic_vector(7 downto 0);
        sum: out std_logic_vector(7 downto 0);
        cout: out std_logic);
    end component;
    
        signal a, b: std_logic_vector(7 downto 0);
        signal sum: std_logic_vector(7 downto 0);
        signal cout: std_logic;

begin
    dut_instance: RCA8
    port map(a=>a,b=>b,sum=>sum,cout=>cout);

    process

    begin

        a<="01010011";
        b<="00110011";

    wait for 1 fs;

        a<="10110111";
        b<="00010111";

    wait for 1 fs;

    end process;
end architecture;

Lab2/210050037/Q2/RCA8.vcd
$date
  Fri Feb  3 23:55:40 2023
$end
$version
  GHDL v0
$end
$timescale
  1 fs
$end
$scope module standard $end
$upscope $end
$scope module std_logic_1164 $end
$upscope $end
$scope module testbench_rca8 $end
$var reg 8 ! a[7:0] $end
$var reg 8 " b[7:0] $end
$var reg 8 # sum[7:0] $end
$var reg 1 $ cout $end
$scope module dut_instance $end
$var reg 8 % a[7:0] $end
$var reg 8 & b[7:0] $end
$var reg 8 ' sum[7:0] $end
$var reg 1 ( cout $end
$var reg 1 ) cin $end
$var reg 1 * temp $end
$var reg 1 + temp1 $end
$var reg 1 , temp2 $end
$var reg 1 - temp3 $end
$var reg 1 . temp4 $end
$var reg 1 / temp5 $end
$var reg 1 0 temp6 $end
$var reg 1 1 temp7 $end
$scope module dut_instance $end
$var reg 1 2 a $end
$var reg 1 3 b $end
$var reg 1 4 c $end
$var reg 1 5 sum $end
$var reg 1 6 cout $end
$upscope $end
$scope module dut_instance1 $end
$var reg 1 7 a $end
$var reg 1 8 b $end
$var reg 1 9 c $end
$var reg 1 : sum $end
$var reg 1 ; cout $end
$upscope $end
$scope module dut_instance2 $end
$var reg 1 < a $end
$var reg 1 = b $end
$var reg 1 > c $end
$var reg 1 ? sum $end
$var reg 1 @ cout $end
$upscope $end
$scope module dut_instance3 $end
$var reg 1 A a $end
$var reg 1 B b $end
$var reg 1 C c $end
$var reg 1 D sum $end
$var reg 1 E cout $end
$upscope $end
$scope module dut_instance4 $end
$var reg 1 F a $end
$var reg 1 G b $end
$var reg 1 H c $end
$var reg 1 I sum $end
$var reg 1 J cout $end
$upscope $end
$scope module dut_instance5 $end
$var reg 1 K a $end
$var reg 1 L b $end
$var reg 1 M c $end
$var reg 1 N sum $end
$var reg 1 O cout $end
$upscope $end
$scope module dut_instance6 $end
$var reg 1 P a $end
$var reg 1 Q b $end
$var reg 1 R c $end
$var reg 1 S sum $end
$var reg 1 T cout $end
$upscope $end
$scope module dut_instance7 $end
$var reg 1 U a $end
$var reg 1 V b $end
$var reg 1 W c $end
$var reg 1 X sum $end
$var reg 1 Y cout $end
$upscope $end
$upscope $end
$upscope $end
$enddefinitions $end
#0
b01010011 !
b00110011 "
b10000110 #
0$
b01010011 %
b00110011 &
b10000110 '
0(
0)
1*
1+
0,
0-
1.
1/
10
01
12
13
04
05
16
17
18
19
1:
1;
0<
0=
1>
1?
0@
0A
0B
0C
0D
0E
1F
1G
0H
0I
1J
0K
1L
1M
0N
1O
1P
0Q
1R
0S
1T
0U
0V
1W
1X
0Y
#1
b10110111 !
b00010111 "
b11001110 #
0$
b10110111 %
b00010111 &
b11001110 '
0(
1,
00
01
1<
1=
1@
1C
1D
1K
0L
0P
1S
0T
1U
0W
1X
0Y
#2
b01010011 !
b00110011 "
b10000110 #
b01010011 %
b00110011 &
b10000110 '
0,
10
0<
0=
0@
0C
0D
0K
1L
1P
0S
1T
0U
1W
1X
#3
b10110111 !
b00010111 "
b11001110 #
0$
b10110111 %
b00010111 &
b11001110 '
0(
1,
00
01
1<
1=
1@
1C
1D
1K
0L
0P
1S
0T
1U
0W
1X
0Y
#4
b01010011 !
b00110011 "
b10000110 #
b01010011 %
b00110011 &
b10000110 '
0,
10
0<
0=
0@
0C
0D
0K
1L
1P
0S
1T
0U
1W
1X
#5
b10110111 !
b00010111 "
b11001110 #
0$
b10110111 %
b00010111 &
b11001110 '
0(
1,
00
01
1<
1=
1@
1C
1D
1K
0L
0P
1S
0T
1U
0W
1X
0Y
#6
b01010011 !
b00110011 "
b10000110 #
b01010011 %
b00110011 &
b10000110 '
0,
10
0<
0=
0@
0C
0D
0K
1L
1P
0S
1T
0U
1W
1X
#7
b10110111 !
b00010111 "
b11001110 #
0$
b10110111 %
b00010111 &
b11001110 '
0(
1,
00
01
1<
1=
1@
1C
1D
1K
0L
0P
1S
0T
1U
0W
1X
0Y
#8
b01010011 !
b00110011 "
b10000110 #
b01010011 %
b00110011 &
b10000110 '
0,
10
0<
0=
0@
0C
0D
0K
1L
1P
0S
1T
0U
1W
1X
#9
b10110111 !
b00010111 "
b11001110 #
0$
b10110111 %
b00010111 &
b11001110 '
0(
1,
00
01
1<
1=
1@
1C
1D
1K
0L
0P
1S
0T
1U
0W
1X
0Y
#10
b01010011 !
b00110011 "
b10000110 #
b01010011 %
b00110011 &
b10000110 '
0,
10
0<
0=
0@
0C
0D
0K
1L
1P
0S
1T
0U
1W
1X
