Lab2/210050037/Q1/and.vhd
library IEEE;
use IEEE.std_logic_1164.all;

entity AND_Gate is
    port(x1: in std_logic;
    x2: in std_logic;
    y: out std_logic);
    end entity;
    
architecture behaviour of AND_Gate is
begin
    y<= x1 and x2;
end architecture;

Lab2/210050037/Q1/and_tb.vhd
library IEEE;
use IEEE.std_logic_1164.all;

entity Testbench is
end entity;

architecture tb of Testbench is

    signal x1,x2: std_logic;
    signal g: std_logic;

    component AND_Gate is
        port(x1: in std_logic;
    x2: in std_logic;
    y: out std_logic);
    end component;
    
begin
    dut_instance: AND_Gate port map (
        x1=>x1,
        x2=>x2,
        y=>g
    );

    process

    begin

    x1<='0';
    x2<='0' ;

    wait for 1 fs;

    x1<='0';
    x2<='1' ;

    wait for 1 fs;

    x1<='1';
    x2<='0' ;

    wait for 1 fs;

    x1<='1';
    x2<='1' ;

    wait for 1 fs;

    end process;
end architecture;

Lab2/and.vcd
$date
  Fri Feb  3 23:31:43 2023
$end
$version
  GHDL v0
$end
$timescale
  1 fs
$end
$scope module standard $end
$upscope $end
$scope module std_logic_1164 $end
$upscope $end
$scope module testbench $end
$var reg 1 ! x1 $end
$var reg 1 " x2 $end
$var reg 1 # g $end
$scope module dut_instance $end
$var reg 1 $ x1 $end
$var reg 1 % x2 $end
$var reg 1 & y $end
$upscope $end
$upscope $end
$enddefinitions $end
#0
0!
0"
0#
0$
0%
0&
#1
1"
1%
#2
1!
0"
1$
0%
#3
1"
1#
1%
1&
#4
0!
0"
0#
0$
0%
0&
#5
1"
1%
#6
1!
0"
1$
0%
#7
1"
1#
1%
1&
#8
0!
0"
0#
0$
0%
0&
#9
1"
1%
#10
1!
0"
1$
0%
