Lab2/210050037/Q1/or.vhd
library IEEE;
use IEEE.std_logic_1164.all;

entity OR_Gate is
    port(x1: in std_logic;
    x2: in std_logic;
    y: out std_logic);
    end entity;
    
architecture behaviour of OR_Gate is
begin
    y<= x1 or x2;
end architecture;

Lab2/enc4x2.vhd
library IEEE;
use IEEE.std_logic_1164.all;

entity encoder4x2 is
    port(I: in std_logic_vector (3 downto 0);
    Y: out std_logic_vector(1 downto 0));
end entity;
    
architecture behaviour of encoder4x2 is
    component OR_Gate is
        port(x1: in std_logic;
        x2: in std_logic;
        y: out std_logic);
        end component;
        signal temp1,temp2: std_logic;
        begin
            dut_instance: OR_Gate
    port map(x1=>I(3) ,x2=>I(2) ,y=>temp1);

                Y(1) <= temp1;

            dut_instance1: OR_Gate
    port map(x1=>I(3) ,x2=>I(1) ,y=>temp2);
             
                Y(0) <= temp2;              
end architecture;

Lab2/enc4x2_tb.vhd
library IEEE;
use IEEE.std_logic_1164.all;

entity Testbench_enc is
end entity;

architecture tb of Testbench_enc is


    component encoder4x2 is
        port(I: in std_logic_vector (3 downto 0);
        Y: out std_logic_vector(1 downto 0));
    end component;
    
    signal I:std_logic_vector (3 downto 0);
    signal Y: std_logic_vector(1 downto 0);

begin
    dut_instance: encoder4x2
    port map(I=>I,Y=>Y);

    process

    begin

        I<="0001";

    wait for 1 fs;

        I<="0010";

    wait for 1 fs;

        I<="0100";

    wait for 1 fs;

        I<="1000";

    wait for 1 fs;
    end process;
end architecture;

Lab2/enc.vcd
$date
  Sun Jan 29 16:29:04 2023
$end
$version
  GHDL v0
$end
$timescale
  1 fs
$end
$scope module standard $end
$upscope $end
$scope module std_logic_1164 $end
$upscope $end
$scope module testbench_enc $end
$var reg 4 ! i[3:0] $end
$var reg 2 " y[1:0] $end
$scope module dut_instance $end
$var reg 4 # i[3:0] $end
$var reg 2 $ y[1:0] $end
$var reg 1 % temp1 $end
$var reg 1 & temp2 $end
$scope module dut_instance $end
$var reg 1 ' x1 $end
$var reg 1 ( x2 $end
$var reg 1 ) y $end
$upscope $end
$scope module dut_instance1 $end
$var reg 1 * x1 $end
$var reg 1 + x2 $end
$var reg 1 , y $end
$upscope $end
$upscope $end
$upscope $end
$enddefinitions $end
#0
b0001 !
b00 "
b0001 #
b00 $
0%
0&
0'
0(
0)
0*
0+
0,
#1
b0010 !
b01 "
b0010 #
b01 $
1&
1+
1,
#2
b0100 !
b10 "
b0100 #
b10 $
1%
0&
1(
1)
0+
0,
#3
b1000 !
b11 "
b1000 #
b11 $
1&
1'
0(
1*
1,
#4
b0001 !
b00 "
b0001 #
b00 $
0%
0&
0'
0)
0*
0,
#5
b0010 !
b01 "
b0010 #
b01 $
1&
1+
1,
#6
b0100 !
b10 "
b0100 #
b10 $
1%
0&
1(
1)
0+
0,
#7
b1000 !
b11 "
b1000 #
b11 $
1&
1'
0(
1*
1,
#8
b0001 !
b00 "
b0001 #
b00 $
0%
0&
0'
0)
0*
0,
#9
b0010 !
b01 "
b0010 #
b01 $
1&
1+
1,
#10
b0100 !
b10 "
b0100 #
b10 $
1%
0&
1(
1)
0+
0,
